dkdrlahel2/__init__.py
dkdrlahel2/__main__.py
dkdrlahel2/adb_handler.py
dkdrlahel2/config_manager.py
dkdrlahel2/csv_handler.py
dkdrlahel2/feature_handler.py
dkdrlahel2/game_data_getter.py
dkdrlahel2/helper.py
dkdrlahel2/item.py
dkdrlahel2/locale_handler.py
dkdrlahel2/managed_item.py
dkdrlahel2/parse_save.py
dkdrlahel2/patcher.py
dkdrlahel2/root_handler.py
dkdrlahel2/serialise_save.py
dkdrlahel2/server_handler.py
dkdrlahel2/tracker.py
dkdrlahel2/updater.py
dkdrlahel2/user_input_handler.py
dkdrlahel2/edits/__init__.py
dkdrlahel2/edits/basic/__init__.py
dkdrlahel2/edits/basic/basic_items.py
dkdrlahel2/edits/basic/catfruit.py
dkdrlahel2/edits/basic/catseyes.py
dkdrlahel2/edits/basic/ototo_base_mats.py
dkdrlahel2/edits/basic/talent_orbs.py
dkdrlahel2/edits/basic/talent_orbs_new.py
dkdrlahel2/edits/cats/__init__.py
dkdrlahel2/edits/cats/cat_helper.py
dkdrlahel2/edits/cats/cat_id_selector.py
dkdrlahel2/edits/cats/chara_drop.py
dkdrlahel2/edits/cats/clear_cat_guide.py
dkdrlahel2/edits/cats/evolve_cats.py
dkdrlahel2/edits/cats/get_remove_cats.py
dkdrlahel2/edits/cats/talents.py
dkdrlahel2/edits/cats/upgrade_blue.py
dkdrlahel2/edits/cats/upgrade_cats.py
dkdrlahel2/edits/gamototo/__init__.py
dkdrlahel2/edits/gamototo/fix_gamatoto.py
dkdrlahel2/edits/gamototo/gamatoto_xp.py
dkdrlahel2/edits/gamototo/helpers.py
dkdrlahel2/edits/gamototo/ototo_cat_cannon.py
dkdrlahel2/edits/levels/__init__.py
dkdrlahel2/edits/levels/aku.py
dkdrlahel2/edits/levels/allow_filibuster_clearing.py
dkdrlahel2/edits/levels/behemoth_culling.py
dkdrlahel2/edits/levels/clear_tutorial.py
dkdrlahel2/edits/levels/enigma_stages.py
dkdrlahel2/edits/levels/event_stages.py
dkdrlahel2/edits/levels/gauntlet.py
dkdrlahel2/edits/levels/itf_timed_scores.py
dkdrlahel2/edits/levels/legend_quest.py
dkdrlahel2/edits/levels/main_story.py
dkdrlahel2/edits/levels/outbreaks.py
dkdrlahel2/edits/levels/story_level_id_selector.py
dkdrlahel2/edits/levels/towers.py
dkdrlahel2/edits/levels/treasures.py
dkdrlahel2-0.0.4.dist-info/METADATA
dkdrlahel2-0.0.4.dist-info/WHEEL
dkdrlahel2-0.0.4.dist-info/top_level.txt
dkdrlahel2-0.0.4.dist-info/RECORD
